neon_client/__init__.py
neon_client/__version__.py
neon_client/client.py
neon_client/exceptions.py
neon_client/schema.py
neon_client/utils.py
neon_client-0.1.0.dist-info/LICENSE
neon_client-0.1.0.dist-info/METADATA
neon_client-0.1.0.dist-info/WHEEL
neon_client-0.1.0.dist-info/top_level.txt
neon_client-0.1.0.dist-info/RECORD
