Metadata-Version: 2.1
Name: neon-client
Version: 0.1.0
Summary: An API Client for the Neon API.
Home-page: https://github.com/kennethreitz/neon-client
Author: Kenneth Reitz
Author-email: me@kennethreitz.org
License: Apache 2.0
Classifier: License :: OSI Approved :: Apache Software License
Classifier: Programming Language :: Python
Classifier: Programming Language :: Python :: 3
Classifier: Programming Language :: Python :: 3.10
Classifier: Programming Language :: Python :: 3.11
Classifier: Programming Language :: Python :: 3.12
Classifier: Programming Language :: Python :: Implementation :: CPython
Classifier: Programming Language :: Python :: Implementation :: PyPy
Requires-Python: >=3.10.0
License-File: LICENSE
Requires-Dist: requests
Requires-Dist: pydantic >=2.0.0
